/**
 * Obfuscator: Binsecure,   Decompiler: Procyon
 * De-obfuscated by Gopro336
 */
package com.krazzzzymonkey.catalyst.managers;

import com.krazzzzymonkey.catalyst.module.Modules;
import com.krazzzzymonkey.catalyst.gui.click.elements.Frame;
import com.krazzzzymonkey.catalyst.module.ModuleCategory;
import com.krazzzzymonkey.catalyst.utils.visual.GLUtils;
import com.krazzzzymonkey.catalyst.gui.click.ClickGui;

public class GuiManager extends ClickGui
{
    public void Init() {
        // 
        // This method could not be decompiled.
        // 
        // Original Bytecode:
        // 
        //     3: nop            
        //     4: nop            
        //     5: nop            
        //     6: athrow         
        //     7: athrow         
        //     8: goto            12
        //    11: athrow         
        //    12: invokestatic    com/krazzzzymonkey/catalyst/utils/visual/GLUtils.getFullScreenWidth:()I
        //    15: goto            19
        //    18: athrow         
        //    19: istore_1       
        //    20: iconst_1       
        //    21: istore_2       
        //    22: bipush          10
        //    24: istore_3       
        //    25: goto            28
        //    28: goto            31
        //    31: goto            35
        //    34: athrow         
        //    35: invokestatic    com/krazzzzymonkey/catalyst/module/ModuleCategory.values:()[Lcom/krazzzzymonkey/catalyst/module/ModuleCategory;
        //    38: goto            42
        //    41: athrow         
        //    42: astore          4
        //    44: aload           4
        //    46: arraylength    
        //    47: istore          5
        //    49: iconst_0       
        //    50: goto            53
        //    53: goto            56
        //    56: istore          6
        //    58: iload           6
        //    60: iload           5
        //    62: if_icmpge       1635
        //    65: aload           4
        //    67: iload           6
        //    69: aaload         
        //    70: astore          7
        //    72: sipush          210
        //    75: istore          8
        //    77: bipush          100
        //    79: istore          9
        //    81: iconst_0       
        //    82: istore          10
        //    84: new             Ljava/lang/StringBuilder;
        //    87: dup            
        //    88: goto            92
        //    91: athrow         
        //    92: invokespecial   java/lang/StringBuilder.<init>:()V
        //    95: goto            99
        //    98: athrow         
        //    99: aload           7
        //   101: goto            105
        //   104: athrow         
        //   105: invokevirtual   com/krazzzzymonkey/catalyst/module/ModuleCategory.toString:()Ljava/lang/String;
        //   108: goto            112
        //   111: athrow         
        //   112: goto            116
        //   115: athrow         
        //   116: invokevirtual   java/lang/String.toLowerCase:()Ljava/lang/String;
        //   119: goto            123
        //   122: athrow         
        //   123: iconst_0       
        //   124: goto            128
        //   127: athrow         
        //   128: invokevirtual   java/lang/String.charAt:(I)C
        //   131: goto            135
        //   134: athrow         
        //   135: goto            139
        //   138: athrow         
        //   139: invokestatic    java/lang/Character.toString:(C)Ljava/lang/String;
        //   142: goto            146
        //   145: athrow         
        //   146: goto            150
        //   149: athrow         
        //   150: invokevirtual   java/lang/String.toUpperCase:()Ljava/lang/String;
        //   153: goto            157
        //   156: athrow         
        //   157: goto            161
        //   160: athrow         
        //   161: invokevirtual   java/lang/StringBuilder.append:(Ljava/lang/String;)Ljava/lang/StringBuilder;
        //   164: goto            168
        //   167: athrow         
        //   168: aload           7
        //   170: goto            173
        //   173: goto            176
        //   176: goto            180
        //   179: athrow         
        //   180: invokevirtual   com/krazzzzymonkey/catalyst/module/ModuleCategory.toString:()Ljava/lang/String;
        //   183: goto            187
        //   186: athrow         
        //   187: goto            190
        //   190: goto            193
        //   193: goto            197
        //   196: athrow         
        //   197: invokevirtual   java/lang/String.toLowerCase:()Ljava/lang/String;
        //   200: goto            204
        //   203: athrow         
        //   204: iconst_1       
        //   205: goto            209
        //   208: athrow         
        //   209: invokevirtual   java/lang/String.substring:(I)Ljava/lang/String;
        //   212: goto            216
        //   215: athrow         
        //   216: goto            220
        //   219: athrow         
        //   220: invokevirtual   java/lang/StringBuilder.append:(Ljava/lang/String;)Ljava/lang/StringBuilder;
        //   223: goto            227
        //   226: athrow         
        //   227: goto            231
        //   230: athrow         
        //   231: invokevirtual   java/lang/StringBuilder.toString:()Ljava/lang/String;
        //   234: goto            238
        //   237: athrow         
        //   238: astore          11
        //   240: new             Lcom/krazzzzymonkey/catalyst/gui/click/elements/Frame;
        //   243: dup            
        //   244: goto            247
        //   247: goto            250
        //   250: iload_2        
        //   251: iload_3        
        //   252: iload           9
        //   254: iload           8
        //   256: aload           11
        //   258: goto            262
        //   261: athrow         
        //   262: invokespecial   com/krazzzzymonkey/catalyst/gui/click/elements/Frame.<init>:(IIIILjava/lang/String;)V
        //   265: goto            269
        //   268: athrow         
        //   269: astore          12
        //   271: goto            275
        //   274: athrow         
        //   275: invokestatic    com/krazzzzymonkey/catalyst/managers/ModuleManager.getModules:()Ljava/util/ArrayList;
        //   278: goto            282
        //   281: athrow         
        //   282: goto            286
        //   285: athrow         
        //   286: invokevirtual   java/util/ArrayList.iterator:()Ljava/util/Iterator;
        //   289: goto            293
        //   292: athrow         
        //   293: astore          13
        //   295: aload           13
        //   297: goto            301
        //   300: athrow         
        //   301: invokeinterface java/util/Iterator.hasNext:()Z
        //   306: goto            310
        //   309: athrow         
        //   310: ifeq            1546
        //   313: aload           13
        //   315: goto            319
        //   318: athrow         
        //   319: invokeinterface java/util/Iterator.next:()Ljava/lang/Object;
        //   324: goto            328
        //   327: athrow         
        //   328: checkcast       Lcom/krazzzzymonkey/catalyst/module/Modules;
        //   331: astore          14
        //   333: aload           14
        //   335: goto            338
        //   338: goto            341
        //   341: goto            345
        //   344: athrow         
        //   345: invokevirtual   com/krazzzzymonkey/catalyst/module/Modules.getCategory:()Lcom/krazzzzymonkey/catalyst/module/ModuleCategory;
        //   348: goto            352
        //   351: athrow         
        //   352: aload           7
        //   354: if_acmpne       1543
        //   357: new             Lcom/krazzzzymonkey/catalyst/managers/GuiManager$1;
        //   360: dup            
        //   361: aload_0        
        //   362: iconst_0       
        //   363: iconst_0       
        //   364: iload           9
        //   366: bipush          14
        //   368: aload           12
        //   370: aload           14
        //   372: goto            376
        //   375: athrow         
        //   376: invokevirtual   com/krazzzzymonkey/catalyst/module/Modules.getName:()Ljava/lang/String;
        //   379: goto            383
        //   382: athrow         
        //   383: aload           14
        //   385: aload           14
        //   387: goto            391
        //   390: athrow         
        //   391: invokespecial   com/krazzzzymonkey/catalyst/managers/GuiManager$1.<init>:(Lcom/krazzzzymonkey/catalyst/managers/GuiManager;IIIILcom/krazzzzymonkey/catalyst/gui/click/base/Component;Ljava/lang/String;Lcom/krazzzzymonkey/catalyst/module/Modules;Lcom/krazzzzymonkey/catalyst/module/Modules;)V
        //   394: goto            398
        //   397: athrow         
        //   398: astore          15
        //   400: aload           15
        //   402: new             Lcom/krazzzzymonkey/catalyst/managers/GuiManager$2;
        //   405: dup            
        //   406: aload_0        
        //   407: aload           14
        //   409: goto            413
        //   412: athrow         
        //   413: invokespecial   com/krazzzzymonkey/catalyst/managers/GuiManager$2.<init>:(Lcom/krazzzzymonkey/catalyst/managers/GuiManager;Lcom/krazzzzymonkey/catalyst/module/Modules;)V
        //   416: goto            420
        //   419: athrow         
        //   420: goto            424
        //   423: athrow         
        //   424: invokevirtual   com/krazzzzymonkey/catalyst/gui/click/elements/ExpandingButton.addListner:(Lcom/krazzzzymonkey/catalyst/gui/click/listener/ComponentClickListener;)V
        //   427: goto            431
        //   430: athrow         
        //   431: aload           15
        //   433: aload           14
        //   435: goto            439
        //   438: athrow         
        //   439: invokevirtual   com/krazzzzymonkey/catalyst/module/Modules.isToggled:()Z
        //   442: goto            446
        //   445: athrow         
        //   446: goto            450
        //   449: athrow         
        //   450: invokevirtual   com/krazzzzymonkey/catalyst/gui/click/elements/ExpandingButton.setEnabled:(Z)V
        //   453: goto            457
        //   456: athrow         
        //   457: aload           14
        //   459: goto            463
        //   462: athrow         
        //   463: invokevirtual   com/krazzzzymonkey/catalyst/module/Modules.getValues:()Ljava/util/ArrayList;
        //   466: goto            470
        //   469: athrow         
        //   470: goto            474
        //   473: athrow         
        //   474: invokevirtual   java/util/ArrayList.isEmpty:()Z
        //   477: goto            481
        //   480: athrow         
        //   481: ifne            1465
        //   484: aload           14
        //   486: goto            490
        //   489: athrow         
        //   490: invokevirtual   com/krazzzzymonkey/catalyst/module/Modules.getValues:()Ljava/util/ArrayList;
        //   493: goto            497
        //   496: athrow         
        //   497: goto            501
        //   500: athrow         
        //   501: invokevirtual   java/util/ArrayList.iterator:()Ljava/util/Iterator;
        //   504: goto            508
        //   507: athrow         
        //   508: astore          16
        //   510: aload           16
        //   512: goto            516
        //   515: athrow         
        //   516: invokeinterface java/util/Iterator.hasNext:()Z
        //   521: goto            525
        //   524: athrow         
        //   525: ifeq            1465
        //   528: aload           16
        //   530: goto            534
        //   533: athrow         
        //   534: invokeinterface java/util/Iterator.next:()Ljava/lang/Object;
        //   539: goto            543
        //   542: athrow         
        //   543: checkcast       Lcom/krazzzzymonkey/catalyst/value/Value;
        //   546: astore          17
        //   548: aload           17
        //   550: instanceof      Lcom/krazzzzymonkey/catalyst/value/types/BooleanValue;
        //   553: ifeq            712
        //   556: aload           17
        //   558: checkcast       Lcom/krazzzzymonkey/catalyst/value/types/BooleanValue;
        //   561: astore          18
        //   563: new             Lcom/krazzzzymonkey/catalyst/gui/click/elements/CheckButton;
        //   566: dup            
        //   567: iconst_0       
        //   568: iconst_0       
        //   569: aload           15
        //   571: goto            575
        //   574: athrow         
        //   575: invokevirtual   com/krazzzzymonkey/catalyst/gui/click/elements/ExpandingButton.getDimension:()Ljava/awt/Dimension;
        //   578: goto            582
        //   581: athrow         
        //   582: goto            585
        //   585: goto            588
        //   588: getfield        java/awt/Dimension.width:I
        //   591: bipush          14
        //   593: aload           15
        //   595: aload           18
        //   597: goto            601
        //   600: athrow         
        //   601: invokevirtual   com/krazzzzymonkey/catalyst/value/types/BooleanValue.getName:()Ljava/lang/String;
        //   604: goto            608
        //   607: athrow         
        //   608: aload           18
        //   610: goto            614
        //   613: athrow         
        //   614: invokevirtual   com/krazzzzymonkey/catalyst/value/types/BooleanValue.getValue:()Ljava/lang/Object;
        //   617: goto            621
        //   620: athrow         
        //   621: checkcast       Ljava/lang/Boolean;
        //   624: goto            627
        //   627: goto            630
        //   630: goto            634
        //   633: athrow         
        //   634: invokevirtual   java/lang/Boolean.booleanValue:()Z
        //   637: goto            641
        //   640: athrow         
        //   641: aconst_null    
        //   642: goto            646
        //   645: athrow         
        //   646: invokespecial   com/krazzzzymonkey/catalyst/gui/click/elements/CheckButton.<init>:(IIIILcom/krazzzzymonkey/catalyst/gui/click/base/Component;Ljava/lang/String;ZLcom/krazzzzymonkey/catalyst/value/types/ModeValue;)V
        //   649: goto            653
        //   652: athrow         
        //   653: astore          19
        //   655: aload           19
        //   657: new             Lcom/krazzzzymonkey/catalyst/managers/GuiManager$3;
        //   660: dup            
        //   661: aload_0        
        //   662: aload           14
        //   664: aload           18
        //   666: goto            670
        //   669: athrow         
        //   670: invokespecial   com/krazzzzymonkey/catalyst/managers/GuiManager$3.<init>:(Lcom/krazzzzymonkey/catalyst/managers/GuiManager;Lcom/krazzzzymonkey/catalyst/module/Modules;Lcom/krazzzzymonkey/catalyst/value/types/BooleanValue;)V
        //   673: goto            677
        //   676: athrow         
        //   677: goto            681
        //   680: athrow         
        //   681: invokevirtual   com/krazzzzymonkey/catalyst/gui/click/elements/CheckButton.addListeners:(Lcom/krazzzzymonkey/catalyst/gui/click/listener/CheckButtonClickListener;)V
        //   684: goto            688
        //   687: athrow         
        //   688: aload           15
        //   690: goto            693
        //   693: goto            696
        //   696: aload           19
        //   698: goto            702
        //   701: athrow         
        //   702: invokevirtual   com/krazzzzymonkey/catalyst/gui/click/elements/ExpandingButton.addComponent:(Lcom/krazzzzymonkey/catalyst/gui/click/base/Component;)V
        //   705: goto            709
        //   708: athrow         
        //   709: goto            1462
        //   712: aload           17
        //   714: instanceof      Lcom/krazzzzymonkey/catalyst/value/sliders/DoubleValue;
        //   717: ifeq            889
        //   720: goto            723
        //   723: goto            726
        //   726: aload           17
        //   728: checkcast       Lcom/krazzzzymonkey/catalyst/value/sliders/DoubleValue;
        //   731: astore          18
        //   733: new             Lcom/krazzzzymonkey/catalyst/gui/click/elements/Slider;
        //   736: dup            
        //   737: aload           18
        //   739: goto            742
        //   742: goto            745
        //   745: goto            749
        //   748: athrow         
        //   749: invokevirtual   com/krazzzzymonkey/catalyst/value/sliders/DoubleValue.getMin:()D
        //   752: goto            756
        //   755: athrow         
        //   756: goto            760
        //   759: athrow         
        //   760: invokestatic    java/lang/Double.valueOf:(D)Ljava/lang/Double;
        //   763: goto            767
        //   766: athrow         
        //   767: aload           18
        //   769: goto            773
        //   772: athrow         
        //   773: invokevirtual   com/krazzzzymonkey/catalyst/value/sliders/DoubleValue.getMax:()D
        //   776: goto            780
        //   779: athrow         
        //   780: goto            784
        //   783: athrow         
        //   784: invokestatic    java/lang/Double.valueOf:(D)Ljava/lang/Double;
        //   787: goto            791
        //   790: athrow         
        //   791: aload           18
        //   793: goto            797
        //   796: athrow         
        //   797: invokevirtual   com/krazzzzymonkey/catalyst/value/sliders/DoubleValue.getValue:()Ljava/lang/Double;
        //   800: goto            804
        //   803: athrow         
        //   804: aload           15
        //   806: aload           18
        //   808: goto            812
        //   811: athrow         
        //   812: invokevirtual   com/krazzzzymonkey/catalyst/value/sliders/DoubleValue.getName:()Ljava/lang/String;
        //   815: goto            819
        //   818: athrow         
        //   819: goto            823
        //   822: athrow         
        //   823: invokespecial   com/krazzzzymonkey/catalyst/gui/click/elements/Slider.<init>:(Ljava/lang/Number;Ljava/lang/Number;Ljava/lang/Number;Lcom/krazzzzymonkey/catalyst/gui/click/base/Component;Ljava/lang/String;)V
        //   826: goto            830
        //   829: athrow         
        //   830: astore          19
        //   832: aload           19
        //   834: new             Lcom/krazzzzymonkey/catalyst/managers/GuiManager$4;
        //   837: dup            
        //   838: aload_0        
        //   839: goto            842
        //   842: goto            845
        //   845: aload           14
        //   847: aload           17
        //   849: goto            853
        //   852: athrow         
        //   853: invokespecial   com/krazzzzymonkey/catalyst/managers/GuiManager$4.<init>:(Lcom/krazzzzymonkey/catalyst/managers/GuiManager;Lcom/krazzzzymonkey/catalyst/module/Modules;Lcom/krazzzzymonkey/catalyst/value/Value;)V
        //   856: goto            860
        //   859: athrow         
        //   860: goto            864
        //   863: athrow         
        //   864: invokevirtual   com/krazzzzymonkey/catalyst/gui/click/elements/Slider.addListener:(Lcom/krazzzzymonkey/catalyst/gui/click/listener/SliderChangeListener;)V
        //   867: goto            871
        //   870: athrow         
        //   871: aload           15
        //   873: aload           19
        //   875: goto            879
        //   878: athrow         
        //   879: invokevirtual   com/krazzzzymonkey/catalyst/gui/click/elements/ExpandingButton.addComponent:(Lcom/krazzzzymonkey/catalyst/gui/click/base/Component;)V
        //   882: goto            886
        //   885: athrow         
        //   886: goto            1462
        //   889: goto            892
        //   892: goto            895
        //   895: aload           17
        //   897: instanceof      Lcom/krazzzzymonkey/catalyst/value/sliders/IntegerValue;
        //   900: ifeq            1066
        //   903: aload           17
        //   905: checkcast       Lcom/krazzzzymonkey/catalyst/value/sliders/IntegerValue;
        //   908: astore          18
        //   910: new             Lcom/krazzzzymonkey/catalyst/gui/click/elements/Slider;
        //   913: dup            
        //   914: aload           18
        //   916: goto            920
        //   919: athrow         
        //   920: invokevirtual   com/krazzzzymonkey/catalyst/value/sliders/IntegerValue.getMin:()I
        //   923: goto            927
        //   926: athrow         
        //   927: goto            931
        //   930: athrow         
        //   931: invokestatic    java/lang/Integer.valueOf:(I)Ljava/lang/Integer;
        //   934: goto            938
        //   937: athrow         
        //   938: aload           18
        //   940: goto            944
        //   943: athrow         
        //   944: invokevirtual   com/krazzzzymonkey/catalyst/value/sliders/IntegerValue.getMax:()I
        //   947: goto            951
        //   950: athrow         
        //   951: goto            955
        //   954: athrow         
        //   955: invokestatic    java/lang/Integer.valueOf:(I)Ljava/lang/Integer;
        //   958: goto            962
        //   961: athrow         
        //   962: aload           18
        //   964: goto            968
        //   967: athrow         
        //   968: invokevirtual   com/krazzzzymonkey/catalyst/value/sliders/IntegerValue.getValue:()Ljava/lang/Integer;
        //   971: goto            975
        //   974: athrow         
        //   975: aload           15
        //   977: aload           18
        //   979: goto            983
        //   982: athrow         
        //   983: invokevirtual   com/krazzzzymonkey/catalyst/value/sliders/IntegerValue.getName:()Ljava/lang/String;
        //   986: goto            990
        //   989: athrow         
        //   990: goto            993
        //   993: goto            996
        //   996: goto            1000
        //   999: athrow         
        //  1000: invokespecial   com/krazzzzymonkey/catalyst/gui/click/elements/Slider.<init>:(Ljava/lang/Number;Ljava/lang/Number;Ljava/lang/Number;Lcom/krazzzzymonkey/catalyst/gui/click/base/Component;Ljava/lang/String;)V
        //  1003: goto            1007
        //  1006: athrow         
        //  1007: astore          19
        //  1009: goto            1012
        //  1012: goto            1015
        //  1015: aload           19
        //  1017: new             Lcom/krazzzzymonkey/catalyst/managers/GuiManager$5;
        //  1020: dup            
        //  1021: aload_0        
        //  1022: aload           14
        //  1024: aload           17
        //  1026: goto            1030
        //  1029: athrow         
        //  1030: invokespecial   com/krazzzzymonkey/catalyst/managers/GuiManager$5.<init>:(Lcom/krazzzzymonkey/catalyst/managers/GuiManager;Lcom/krazzzzymonkey/catalyst/module/Modules;Lcom/krazzzzymonkey/catalyst/value/Value;)V
        //  1033: goto            1037
        //  1036: athrow         
        //  1037: goto            1041
        //  1040: athrow         
        //  1041: invokevirtual   com/krazzzzymonkey/catalyst/gui/click/elements/Slider.addListener:(Lcom/krazzzzymonkey/catalyst/gui/click/listener/SliderChangeListener;)V
        //  1044: goto            1048
        //  1047: athrow         
        //  1048: aload           15
        //  1050: aload           19
        //  1052: goto            1056
        //  1055: athrow         
        //  1056: invokevirtual   com/krazzzzymonkey/catalyst/gui/click/elements/ExpandingButton.addComponent:(Lcom/krazzzzymonkey/catalyst/gui/click/base/Component;)V
        //  1059: goto            1063
        //  1062: athrow         
        //  1063: goto            1462
        //  1066: aload           17
        //  1068: instanceof      Lcom/krazzzzymonkey/catalyst/value/types/ModeValue;
        //  1071: ifeq            1309
        //  1074: new             Lcom/krazzzzymonkey/catalyst/gui/click/elements/Dropdown;
        //  1077: dup            
        //  1078: iconst_0       
        //  1079: iconst_0       
        //  1080: iload           9
        //  1082: iconst_2       
        //  1083: isub           
        //  1084: bipush          14
        //  1086: aload           12
        //  1088: aload           17
        //  1090: goto            1094
        //  1093: athrow         
        //  1094: invokevirtual   com/krazzzzymonkey/catalyst/value/Value.getName:()Ljava/lang/String;
        //  1097: goto            1101
        //  1100: athrow         
        //  1101: goto            1105
        //  1104: athrow         
        //  1105: invokespecial   com/krazzzzymonkey/catalyst/gui/click/elements/Dropdown.<init>:(IIIILcom/krazzzzymonkey/catalyst/gui/click/base/Component;Ljava/lang/String;)V
        //  1108: goto            1112
        //  1111: athrow         
        //  1112: astore          18
        //  1114: aload           17
        //  1116: checkcast       Lcom/krazzzzymonkey/catalyst/value/types/ModeValue;
        //  1119: astore          19
        //  1121: aload           19
        //  1123: goto            1127
        //  1126: athrow         
        //  1127: invokevirtual   com/krazzzzymonkey/catalyst/value/types/ModeValue.getModes:()[Lcom/krazzzzymonkey/catalyst/value/Mode;
        //  1130: goto            1134
        //  1133: athrow         
        //  1134: astore          20
        //  1136: aload           20
        //  1138: arraylength    
        //  1139: goto            1142
        //  1142: goto            1145
        //  1145: istore          21
        //  1147: iconst_0       
        //  1148: istore          22
        //  1150: iload           22
        //  1152: iload           21
        //  1154: if_icmpge       1291
        //  1157: aload           20
        //  1159: iload           22
        //  1161: aaload         
        //  1162: astore          23
        //  1164: new             Lcom/krazzzzymonkey/catalyst/gui/click/elements/CheckButton;
        //  1167: dup            
        //  1168: iconst_0       
        //  1169: iconst_0       
        //  1170: aload           15
        //  1172: goto            1176
        //  1175: athrow         
        //  1176: invokevirtual   com/krazzzzymonkey/catalyst/gui/click/elements/ExpandingButton.getDimension:()Ljava/awt/Dimension;
        //  1179: goto            1183
        //  1182: athrow         
        //  1183: getfield        java/awt/Dimension.width:I
        //  1186: bipush          14
        //  1188: aload           15
        //  1190: aload           23
        //  1192: goto            1196
        //  1195: athrow         
        //  1196: invokevirtual   com/krazzzzymonkey/catalyst/value/Mode.getName:()Ljava/lang/String;
        //  1199: goto            1203
        //  1202: athrow         
        //  1203: aload           23
        //  1205: goto            1209
        //  1208: athrow         
        //  1209: invokevirtual   com/krazzzzymonkey/catalyst/value/Mode.isToggled:()Z
        //  1212: goto            1216
        //  1215: athrow         
        //  1216: aload           19
        //  1218: goto            1222
        //  1221: athrow         
        //  1222: invokespecial   com/krazzzzymonkey/catalyst/gui/click/elements/CheckButton.<init>:(IIIILcom/krazzzzymonkey/catalyst/gui/click/base/Component;Ljava/lang/String;ZLcom/krazzzzymonkey/catalyst/value/types/ModeValue;)V
        //  1225: goto            1229
        //  1228: athrow         
        //  1229: astore          24
        //  1231: goto            1234
        //  1234: goto            1237
        //  1237: aload           24
        //  1239: new             Lcom/krazzzzymonkey/catalyst/managers/GuiManager$6;
        //  1242: dup            
        //  1243: aload_0        
        //  1244: aload           19
        //  1246: aload           23
        //  1248: goto            1252
        //  1251: athrow         
        //  1252: invokespecial   com/krazzzzymonkey/catalyst/managers/GuiManager$6.<init>:(Lcom/krazzzzymonkey/catalyst/managers/GuiManager;Lcom/krazzzzymonkey/catalyst/value/types/ModeValue;Lcom/krazzzzymonkey/catalyst/value/Mode;)V
        //  1255: goto            1259
        //  1258: athrow         
        //  1259: goto            1263
        //  1262: athrow         
        //  1263: invokevirtual   com/krazzzzymonkey/catalyst/gui/click/elements/CheckButton.addListeners:(Lcom/krazzzzymonkey/catalyst/gui/click/listener/CheckButtonClickListener;)V
        //  1266: goto            1270
        //  1269: athrow         
        //  1270: aload           18
        //  1272: aload           24
        //  1274: goto            1278
        //  1277: athrow         
        //  1278: invokevirtual   com/krazzzzymonkey/catalyst/gui/click/elements/Dropdown.addComponent:(Lcom/krazzzzymonkey/catalyst/gui/click/base/Component;)V
        //  1281: goto            1285
        //  1284: athrow         
        //  1285: iinc            22, 1
        //  1288: goto            1150
        //  1291: aload           15
        //  1293: aload           18
        //  1295: goto            1299
        //  1298: athrow         
        //  1299: invokevirtual   com/krazzzzymonkey/catalyst/gui/click/elements/ExpandingButton.addComponent:(Lcom/krazzzzymonkey/catalyst/gui/click/base/Component;)V
        //  1302: goto            1306
        //  1305: athrow         
        //  1306: goto            1462
        //  1309: aload           17
        //  1311: instanceof      Lcom/krazzzzymonkey/catalyst/value/types/ColorValue;
        //  1314: ifeq            1462
        //  1317: aload           17
        //  1319: checkcast       Lcom/krazzzzymonkey/catalyst/value/types/ColorValue;
        //  1322: astore          18
        //  1324: new             Lcom/krazzzzymonkey/catalyst/gui/click/elements/ColorPicker;
        //  1327: dup            
        //  1328: iconst_0       
        //  1329: iconst_0       
        //  1330: iload           9
        //  1332: bipush          65
        //  1334: aload           18
        //  1336: goto            1340
        //  1339: athrow         
        //  1340: invokevirtual   com/krazzzzymonkey/catalyst/value/types/ColorValue.getValue:()Ljava/lang/Object;
        //  1343: goto            1347
        //  1346: athrow         
        //  1347: checkcast       Ljava/lang/Integer;
        //  1350: goto            1354
        //  1353: athrow         
        //  1354: invokevirtual   java/lang/Integer.intValue:()I
        //  1357: goto            1361
        //  1360: athrow         
        //  1361: aload           18
        //  1363: goto            1367
        //  1366: athrow         
        //  1367: invokevirtual   com/krazzzzymonkey/catalyst/value/types/ColorValue.getRainbow:()Z
        //  1370: goto            1374
        //  1373: athrow         
        //  1374: aload           15
        //  1376: aload           18
        //  1378: goto            1381
        //  1381: goto            1384
        //  1384: goto            1388
        //  1387: athrow         
        //  1388: invokevirtual   com/krazzzzymonkey/catalyst/value/types/ColorValue.getName:()Ljava/lang/String;
        //  1391: goto            1395
        //  1394: athrow         
        //  1395: aload           18
        //  1397: goto            1400
        //  1400: goto            1403
        //  1403: goto            1407
        //  1406: athrow         
        //  1407: invokespecial   com/krazzzzymonkey/catalyst/gui/click/elements/ColorPicker.<init>:(IIIIIZLcom/krazzzzymonkey/catalyst/gui/click/base/Component;Ljava/lang/String;Lcom/krazzzzymonkey/catalyst/value/types/ColorValue;)V
        //  1410: goto            1414
        //  1413: athrow         
        //  1414: astore          19
        //  1416: aload           19
        //  1418: new             Lcom/krazzzzymonkey/catalyst/managers/GuiManager$7;
        //  1421: dup            
        //  1422: aload_0        
        //  1423: aload           17
        //  1425: goto            1429
        //  1428: athrow         
        //  1429: invokespecial   com/krazzzzymonkey/catalyst/managers/GuiManager$7.<init>:(Lcom/krazzzzymonkey/catalyst/managers/GuiManager;Lcom/krazzzzymonkey/catalyst/value/Value;)V
        //  1432: goto            1436
        //  1435: athrow         
        //  1436: goto            1440
        //  1439: athrow         
        //  1440: invokevirtual   com/krazzzzymonkey/catalyst/gui/click/elements/ColorPicker.addListener:(Lcom/krazzzzymonkey/catalyst/gui/click/listener/ColorChangeListener;)V
        //  1443: goto            1447
        //  1446: athrow         
        //  1447: aload           15
        //  1449: aload           19
        //  1451: goto            1455
        //  1454: athrow         
        //  1455: invokevirtual   com/krazzzzymonkey/catalyst/gui/click/elements/ExpandingButton.addComponent:(Lcom/krazzzzymonkey/catalyst/gui/click/base/Component;)V
        //  1458: goto            1462
        //  1461: athrow         
        //  1462: goto            510
        //  1465: new             Lcom/krazzzzymonkey/catalyst/gui/click/elements/KeybindMods;
        //  1468: dup            
        //  1469: iconst_m1      
        //  1470: iconst_0       
        //  1471: bipush          8
        //  1473: bipush          14
        //  1475: goto            1478
        //  1478: goto            1481
        //  1481: aload           15
        //  1483: goto            1486
        //  1486: goto            1489
        //  1489: aload           14
        //  1491: goto            1495
        //  1494: athrow         
        //  1495: invokespecial   com/krazzzzymonkey/catalyst/gui/click/elements/KeybindMods.<init>:(IIIILcom/krazzzzymonkey/catalyst/gui/click/base/Component;Lcom/krazzzzymonkey/catalyst/module/Modules;)V
        //  1498: goto            1502
        //  1501: athrow         
        //  1502: astore          16
        //  1504: aload           15
        //  1506: aload           16
        //  1508: goto            1512
        //  1511: athrow         
        //  1512: invokevirtual   com/krazzzzymonkey/catalyst/gui/click/elements/ExpandingButton.addComponent:(Lcom/krazzzzymonkey/catalyst/gui/click/base/Component;)V
        //  1515: goto            1519
        //  1518: athrow         
        //  1519: goto            1522
        //  1522: goto            1525
        //  1525: aload           12
        //  1527: aload           15
        //  1529: goto            1533
        //  1532: athrow         
        //  1533: invokevirtual   com/krazzzzymonkey/catalyst/gui/click/elements/Frame.addComponent:(Lcom/krazzzzymonkey/catalyst/gui/click/base/Component;)V
        //  1536: goto            1540
        //  1539: athrow         
        //  1540: iinc            10, 1
        //  1543: goto            295
        //  1546: iload_2        
        //  1547: iload           9
        //  1549: iadd           
        //  1550: bipush          10
        //  1552: iadd           
        //  1553: iload_1        
        //  1554: if_icmpge       1567
        //  1557: iload_2        
        //  1558: iload           9
        //  1560: iconst_2       
        //  1561: iadd           
        //  1562: iadd           
        //  1563: istore_2       
        //  1564: goto            1573
        //  1567: bipush          20
        //  1569: istore_2       
        //  1570: iinc            3, 60
        //  1573: aload           12
        //  1575: iconst_1       
        //  1576: goto            1580
        //  1579: athrow         
        //  1580: invokevirtual   com/krazzzzymonkey/catalyst/gui/click/elements/Frame.setMaximizible:(Z)V
        //  1583: goto            1587
        //  1586: athrow         
        //  1587: aload           12
        //  1589: iconst_1       
        //  1590: goto            1594
        //  1593: athrow         
        //  1594: invokevirtual   com/krazzzzymonkey/catalyst/gui/click/elements/Frame.setPinnable:(Z)V
        //  1597: goto            1601
        //  1600: athrow         
        //  1601: aload           7
        //  1603: getstatic       com/krazzzzymonkey/catalyst/module/ModuleCategory.HUD:Lcom/krazzzzymonkey/catalyst/module/ModuleCategory;
        //  1606: if_acmpeq       1629
        //  1609: goto            1612
        //  1612: goto            1615
        //  1615: aload_0        
        //  1616: aload           12
        //  1618: goto            1622
        //  1621: athrow         
        //  1622: invokevirtual   com/krazzzzymonkey/catalyst/managers/GuiManager.addFrame:(Lcom/krazzzzymonkey/catalyst/gui/click/elements/Frame;)V
        //  1625: goto            1629
        //  1628: athrow         
        //  1629: iinc            6, 1
        //  1632: goto            58
        //  1635: getstatic       com/krazzzzymonkey/catalyst/managers/FileManager.CLICKGUI:Ljava/io/File;
        //  1638: goto            1642
        //  1641: athrow         
        //  1642: invokevirtual   java/io/File.exists:()Z
        //  1645: goto            1649
        //  1648: athrow         
        //  1649: ifne            1666
        //  1652: goto            1656
        //  1655: athrow         
        //  1656: invokestatic    com/krazzzzymonkey/catalyst/managers/FileManager.saveClickGui:()V
        //  1659: goto            1663
        //  1662: athrow         
        //  1663: goto            1677
        //  1666: goto            1670
        //  1669: athrow         
        //  1670: invokestatic    com/krazzzzymonkey/catalyst/managers/FileManager.loadClickGui:()V
        //  1673: goto            1677
        //  1676: athrow         
        //  1677: return         
        //  1678: nop            
        //  1679: athrow         
        //  1680: nop            
        //  1681: athrow         
        //  1682: nop            
        //  1683: athrow         
        //  1684: nop            
        //  1685: athrow         
        //  1686: nop            
        //  1687: athrow         
        //  1688: nop            
        //  1689: athrow         
        //  1690: nop            
        //  1691: athrow         
        //  1692: nop            
        //  1693: athrow         
        //  1694: nop            
        //  1695: athrow         
        //  1696: nop            
        //  1697: athrow         
        //  1698: nop            
        //  1699: athrow         
        //  1700: nop            
        //  1701: athrow         
        //  1702: nop            
        //  1703: athrow         
        //  1704: nop            
        //  1705: athrow         
        //  1706: nop            
        //  1707: athrow         
        //  1708: nop            
        //  1709: athrow         
        //  1710: nop            
        //  1711: athrow         
        //  1712: nop            
        //  1713: athrow         
        //  1714: nop            
        //  1715: athrow         
        //  1716: nop            
        //  1717: athrow         
        //  1718: nop            
        //  1719: athrow         
        //  1720: nop            
        //  1721: athrow         
        //  1722: nop            
        //  1723: athrow         
        //  1724: nop            
        //  1725: athrow         
        //    StackMapTable: 01 B9 FF 00 03 00 00 00 01 07 00 08 43 07 00 08 FC 00 00 07 00 02 FF 00 02 00 00 00 01 07 00 08 FC 00 00 07 00 02 FF 00 05 00 00 00 01 07 00 08 FF 00 00 00 01 07 00 02 00 01 01 FE 00 08 01 01 01 02 FF 00 02 00 00 00 01 07 00 08 FF 00 00 00 04 07 00 02 01 01 01 00 00 FF 00 05 00 00 00 01 07 00 08 FF 00 00 00 04 07 00 02 01 01 01 00 01 07 00 16 FF 00 0A 00 06 07 00 02 01 01 01 07 00 16 01 00 01 01 42 01 FC 00 01 01 FF 00 20 00 00 00 01 07 00 08 FF 00 00 00 0B 07 00 02 01 01 01 07 00 16 01 01 07 00 10 01 01 01 00 02 08 00 54 08 00 54 FF 00 05 00 00 00 01 07 00 08 FF 00 00 00 0B 07 00 02 01 01 01 07 00 16 01 01 07 00 10 01 01 01 00 01 07 00 18 FF 00 04 00 00 00 01 07 00 08 FF 00 00 00 0B 07 00 02 01 01 01 07 00 16 01 01 07 00 10 01 01 01 00 02 07 00 18 07 00 10 FF 00 05 00 00 00 01 07 00 08 FF 00 00 00 0B 07 00 02 01 01 01 07 00 16 01 01 07 00 10 01 01 01 00 02 07 00 18 07 00 21 FF 00 02 00 00 00 01 07 00 08 FF 00 00 00 0B 07 00 02 01 01 01 07 00 16 01 01 07 00 10 01 01 01 00 02 07 00 18 07 00 21 FF 00 05 00 00 00 01 07 00 08 FF 00 00 00 0B 07 00 02 01 01 01 07 00 16 01 01 07 00 10 01 01 01 00 02 07 00 18 07 00 21 FF 00 03 00 00 00 01 07 00 08 FF 00 00 00 0B 07 00 02 01 01 01 07 00 16 01 01 07 00 10 01 01 01 00 03 07 00 18 07 00 21 01 FF 00 05 00 00 00 01 07 00 08 FF 00 00 00 0B 07 00 02 01 01 01 07 00 16 01 01 07 00 10 01 01 01 00 02 07 00 18 01 FF 00 02 00 00 00 01 07 00 08 FF 00 00 00 0B 07 00 02 01 01 01 07 00 16 01 01 07 00 10 01 01 01 00 02 07 00 18 01 FF 00 05 00 00 00 01 07 00 08 FF 00 00 00 0B 07 00 02 01 01 01 07 00 16 01 01 07 00 10 01 01 01 00 02 07 00 18 07 00 21 FF 00 02 00 00 00 01 07 00 08 FF 00 00 00 0B 07 00 02 01 01 01 07 00 16 01 01 07 00 10 01 01 01 00 02 07 00 18 07 00 21 FF 00 05 00 00 00 01 07 00 08 FF 00 00 00 0B 07 00 02 01 01 01 07 00 16 01 01 07 00 10 01 01 01 00 02 07 00 18 07 00 21 FF 00 02 00 00 00 01 07 00 08 FF 00 00 00 0B 07 00 02 01 01 01 07 00 16 01 01 07 00 10 01 01 01 00 02 07 00 18 07 00 21 FF 00 05 00 00 00 01 07 00 08 FF 00 00 00 0B 07 00 02 01 01 01 07 00 16 01 01 07 00 10 01 01 01 00 01 07 00 18 FF 00 04 00 0B 07 00 02 01 01 01 07 00 16 01 01 07 00 10 01 01 01 00 02 07 00 18 07 00 10 FF 00 02 00 0B 07 00 02 01 01 01 07 00 16 01 01 07 00 10 01 01 01 00 02 07 00 18 07 00 10 FF 00 02 00 00 00 01 07 00 08 FF 00 00 00 0B 07 00 02 01 01 01 07 00 16 01 01 07 00 10 01 01 01 00 02 07 00 18 07 00 10 FF 00 05 00 00 00 01 07 00 08 FF 00 00 00 0B 07 00 02 01 01 01 07 00 16 01 01 07 00 10 01 01 01 00 02 07 00 18 07 00 21 FF 00 02 00 0B 07 00 02 01 01 01 07 00 16 01 01 07 00 10 01 01 01 00 02 07 00 18 07 00 21 FF 00 02 00 0B 07 00 02 01 01 01 07 00 16 01 01 07 00 10 01 01 01 00 02 07 00 18 07 00 21 FF 00 02 00 00 00 01 07 00 08 FF 00 00 00 0B 07 00 02 01 01 01 07 00 16 01 01 07 00 10 01 01 01 00 02 07 00 18 07 00 21 FF 00 05 00 00 00 01 07 00 08 FF 00 00 00 0B 07 00 02 01 01 01 07 00 16 01 01 07 00 10 01 01 01 00 02 07 00 18 07 00 21 FF 00 03 00 00 00 01 07 00 08 FF 00 00 00 0B 07 00 02 01 01 01 07 00 16 01 01 07 00 10 01 01 01 00 03 07 00 18 07 00 21 01 FF 00 05 00 00 00 01 07 00 08 FF 00 00 00 0B 07 00 02 01 01 01 07 00 16 01 01 07 00 10 01 01 01 00 02 07 00 18 07 00 21 FF 00 02 00 00 00 01 07 00 08 FF 00 00 00 0B 07 00 02 01 01 01 07 00 16 01 01 07 00 10 01 01 01 00 02 07 00 18 07 00 21 FF 00 05 00 00 00 01 07 00 08 FF 00 00 00 0B 07 00 02 01 01 01 07 00 16 01 01 07 00 10 01 01 01 00 01 07 00 18 FF 00 02 00 00 00 01 07 00 08 FF 00 00 00 0B 07 00 02 01 01 01 07 00 16 01 01 07 00 10 01 01 01 00 01 07 00 18 FF 00 05 00 00 00 01 07 00 08 FF 00 00 00 0B 07 00 02 01 01 01 07 00 16 01 01 07 00 10 01 01 01 00 01 07 00 21 FF 00 08 00 0C 07 00 02 01 01 01 07 00 16 01 01 07 00 10 01 01 01 07 00 21 00 02 08 00 F0 08 00 F0 FF 00 02 00 0C 07 00 02 01 01 01 07 00 16 01 01 07 00 10 01 01 01 07 00 21 00 02 08 00 F0 08 00 F0 FF 00 0A 00 00 00 01 07 00 08 FF 00 00 00 0C 07 00 02 01 01 01 07 00 16 01 01 07 00 10 01 01 01 07 00 21 00 07 08 00 F0 08 00 F0 01 01 01 01 07 00 21 FF 00 05 00 00 00 01 07 00 08 FF 00 00 00 0C 07 00 02 01 01 01 07 00 16 01 01 07 00 10 01 01 01 07 00 21 00 01 07 00 3B FF 00 04 00 00 00 01 07 00 08 FF 00 00 00 0D 07 00 02 01 01 01 07 00 16 01 01 07 00 10 01 01 01 07 00 21 07 00 3B 00 00 FF 00 05 00 00 00 01 07 00 08 FF 00 00 00 0D 07 00 02 01 01 01 07 00 16 01 01 07 00 10 01 01 01 07 00 21 07 00 3B 00 01 07 00 46 FF 00 02 00 00 00 01 07 00 08 FF 00 00 00 0D 07 00 02 01 01 01 07 00 16 01 01 07 00 10 01 01 01 07 00 21 07 00 3B 00 01 07 00 46 FF 00 05 00 00 00 01 07 00 08 FF 00 00 00 0D 07 00 02 01 01 01 07 00 16 01 01 07 00 10 01 01 01 07 00 21 07 00 3B 00 01 07 00 4C FC 00 01 07 00 4C FF 00 04 00 00 00 01 07 00 08 FF 00 00 00 0E 07 00 02 01 01 01 07 00 16 01 01 07 00 10 01 01 01 07 00 21 07 00 3B 07 00 4C 00 01 07 00 4C FF 00 07 00 00 00 01 07 00 08 FF 00 00 00 0E 07 00 02 01 01 01 07 00 16 01 01 07 00 10 01 01 01 07 00 21 07 00 3B 07 00 4C 00 01 01 FF 00 07 00 00 00 01 07 00 08 FF 00 00 00 0E 07 00 02 01 01 01 07 00 16 01 01 07 00 10 01 01 01 07 00 21 07 00 3B 07 00 4C 00 01 07 00 4C FF 00 07 00 00 00 01 07 00 08 FF 00 00 00 0E 07 00 02 01 01 01 07 00 16 01 01 07 00 10 01 01 01 07 00 21 07 00 3B 07 00 4C 00 01 07 00 56 FF 00 09 00 0F 07 00 02 01 01 01 07 00 16 01 01 07 00 10 01 01 01 07 00 21 07 00 3B 07 00 4C 07 00 58 00 01 07 00 58 42 07 00 58 FF 00 02 00 00 00 01 07 00 08 FF 00 00 00 0F 07 00 02 01 01 01 07 00 16 01 01 07 00 10 01 01 01 07 00 21 07 00 3B 07 00 4C 07 00 58 00 01 07 00 58 FF 00 05 00 00 00 01 07 00 08 FF 00 00 00 0F 07 00 02 01 01 01 07 00 16 01 01 07 00 10 01 01 01 07 00 21 07 00 3B 07 00 4C 07 00 58 00 01 07 00 10 FF 00 16 00 00 00 01 07 00 08 FF 00 00 00 0F 07 00 02 01 01 01 07 00 16 01 01 07 00 10 01 01 01 07 00 21 07 00 3B 07 00 4C 07 00 58 00 09 08 01 65 08 01 65 07 00 02 01 01 01 01 07 00 3B 07 00 58 FF 00 05 00 00 00 01 07 00 08 FF 00 00 00 0F 07 00 02 01 01 01 07 00 16 01 01 07 00 10 01 01 01 07 00 21 07 00 3B 07 00 4C 07 00 58 00 09 08 01 65 08 01 65 07 00 02 01 01 01 01 07 00 3B 07 00 21 FF 00 06 00 00 00 01 07 00 08 FF 00 00 00 0F 07 00 02 01 01 01 07 00 16 01 01 07 00 10 01 01 01 07 00 21 07 00 3B 07 00 4C 07 00 58 00 0B 08 01 65 08 01 65 07 00 02 01 01 01 01 07 00 3B 07 00 21 07 00 58 07 00 58 FF 00 05 00 00 00 01 07 00 08 FF 00 00 00 0F 07 00 02 01 01 01 07 00 16 01 01 07 00 10 01 01 01 07 00 21 07 00 3B 07 00 4C 07 00 58 00 01 07 00 5E FF 00 0D 00 00 00 01 07 00 08 FF 00 00 00 10 07 00 02 01 01 01 07 00 16 01 01 07 00 10 01 01 01 07 00 21 07 00 3B 07 00 4C 07 00 58 07 00 5E 00 05 07 00 5E 08 01 92 08 01 92 07 00 02 07 00 58 FF 00 05 00 00 00 01 07 00 08 FF 00 00 00 10 07 00 02 01 01 01 07 00 16 01 01 07 00 10 01 01 01 07 00 21 07 00 3B 07 00 4C 07 00 58 07 00 5E 00 02 07 00 5E 07 00 66 FF 00 02 00 00 00 01 07 00 08 FF 00 00 00 10 07 00 02 01 01 01 07 00 16 01 01 07 00 10 01 01 01 07 00 21 07 00 3B 07 00 4C 07 00 58 07 00 5E 00 02 07 00 5E 07 00 66 FF 00 05 00 00 00 01 07 00 08 FF 00 00 00 10 07 00 02 01 01 01 07 00 16 01 01 07 00 10 01 01 01 07 00 21 07 00 3B 07 00 4C 07 00 58 07 00 5E 00 00 FF 00 06 00 00 00 01 07 00 08 FF 00 00 00 10 07 00 02 01 01 01 07 00 16 01 01 07 00 10 01 01 01 07 00 21 07 00 3B 07 00 4C 07 00 58 07 00 5E 00 02 07 00 5E 07 00 58 FF 00 05 00 00 00 01 07 00 08 FF 00 00 00 10 07 00 02 01 01 01 07 00 16 01 01 07 00 10 01 01 01 07 00 21 07 00 3B 07 00 4C 07 00 58 07 00 5E 00 02 07 00 5E 01 FF 00 02 00 00 00 01 07 00 08 FF 00 00 00 10 07 00 02 01 01 01 07 00 16 01 01 07 00 10 01 01 01 07 00 21 07 00 3B 07 00 4C 07 00 58 07 00 5E 00 02 07 00 5E 01 FF 00 05 00 00 00 01 07 00 08 FF 00 00 00 10 07 00 02 01 01 01 07 00 16 01 01 07 00 10 01 01 01 07 00 21 07 00 3B 07 00 4C 07 00 58 07 00 5E 00 00 FF 00 04 00 00 00 01 07 00 08 FF 00 00 00 10 07 00 02 01 01 01 07 00 16 01 01 07 00 10 01 01 01 07 00 21 07 00 3B 07 00 4C 07 00 58 07 00 5E 00 01 07 00 58 FF 00 05 00 00 00 01 07 00 08 FF 00 00 00 10 07 00 02 01 01 01 07 00 16 01 01 07 00 10 01 01 01 07 00 21 07 00 3B 07 00 4C 07 00 58 07 00 5E 00 01 07 00 46 FF 00 02 00 00 00 01 07 00 08 FF 00 00 00 10 07 00 02 01 01 01 07 00 16 01 01 07 00 10 01 01 01 07 00 21 07 00 3B 07 00 4C 07 00 58 07 00 5E 00 01 07 00 46 FF 00 05 00 00 00 01 07 00 08 FF 00 00 00 10 07 00 02 01 01 01 07 00 16 01 01 07 00 10 01 01 01 07 00 21 07 00 3B 07 00 4C 07 00 58 07 00 5E 00 01 01 FF 00 07 00 00 00 01 07 00 08 FF 00 00 00 10 07 00 02 01 01 01 07 00 16 01 01 07 00 10 01 01 01 07 00 21 07 00 3B 07 00 4C 07 00 58 07 00 5E 00 01 07 00 58 FF 00 05 00 00 00 01 07 00 08 FF 00 00 00 10 07 00 02 01 01 01 07 00 16 01 01 07 00 10 01 01 01 07 00 21 07 00 3B 07 00 4C 07 00 58 07 00 5E 00 01 07 00 46 FF 00 02 00 00 00 01 07 00 08 FF 00 00 00 10 07 00 02 01 01 01 07 00 16 01 01 07 00 10 01 01 01 07 00 21 07 00 3B 07 00 4C 07 00 58 07 00 5E 00 01 07 00 46 FF 00 05 00 00 00 01 07 00 08 FF 00 00 00 10 07 00 02 01 01 01 07 00 16 01 01 07 00 10 01 01 01 07 00 21 07 00 3B 07 00 4C 07 00 58 07 00 5E 00 01 07 00 4C FC 00 01 07 00 4C FF 00 04 00 00 00 01 07 00 08 FF 00 00 00 11 07 00 02 01 01 01 07 00 16 01 01 07 00 10 01 01 01 07 00 21 07 00 3B 07 00 4C 07 00 58 07 00 5E 07 00 4C 00 01 07 00 4C FF 00 07 00 00 00 01 07 00 08 FF 00 00 00 11 07 00 02 01 01 01 07 00 16 01 01 07 00 10 01 01 01 07 00 21 07 00 3B 07 00 4C 07 00 58 07 00 5E 07 00 4C 00 01 01 FF 00 07 00 00 00 01 07 00 08 FF 00 00 00 11 07 00 02 01 01 01 07 00 16 01 01 07 00 10 01 01 01 07 00 21 07 00 3B 07 00 4C 07 00 58 07 00 5E 07 00 4C 00 01 07 00 4C FF 00 07 00 00 00 01 07 00 08 FF 00 00 00 11 07 00 02 01 01 01 07 00 16 01 01 07 00 10 01 01 01 07 00 21 07 00 3B 07 00 4C 07 00 58 07 00 5E 07 00 4C 00 01 07 00 56 FF 00 1E 00 00 00 01 07 00 08 FF 00 00 00 13 07 00 02 01 01 01 07 00 16 01 01 07 00 10 01 01 01 07 00 21 07 00 3B 07 00 4C 07 00 58 07 00 5E 07 00 4C 07 00 7E 07 00 80 00 05 08 02 33 08 02 33 01 01 07 00 5E FF 00 05 00 00 00 01 07 00 08 FF 00 00 00 13 07 00 02 01 01 01 07 00 16 01 01 07 00 10 01 01 01 07 00 21 07 00 3B 07 00 4C 07 00 58 07 00 5E 07 00 4C 07 00 7E 07 00 80 00 05 08 02 33 08 02 33 01 01 07 00 88 FF 00 02 00 13 07 00 02 01 01 01 07 00 16 01 01 07 00 10 01 01 01 07 00 21 07 00 3B 07 00 4C 07 00 58 07 00 5E 07 00 4C 07 00 7E 07 00 80 00 05 08 02 33 08 02 33 01 01 07 00 88 FF 00 02 00 13 07 00 02 01 01 01 07 00 16 01 01 07 00 10 01 01 01 07 00 21 07 00 3B 07 00 4C 07 00 58 07 00 5E 07 00 4C 07 00 7E 07 00 80 00 05 08 02 33 08 02 33 01 01 07 00 88 FF 00 0B 00 00 00 01 07 00 08 FF 00 00 00 13 07 00 02 01 01 01 07 00 16 01 01 07 00 10 01 01 01 07 00 21 07 00 3B 07 00 4C 07 00 58 07 00 5E 07 00 4C 07 00 7E 07 00 80 00 08 08 02 33 08 02 33 01 01 01 01 07 00 5E 07 00 80 FF 00 05 00 00 00 01 07 00 08 FF 00 00 00 13 07 00 02 01 01 01 07 00 16 01 01 07 00 10 01 01 01 07 00 21 07 00 3B 07 00 4C 07 00 58 07 00 5E 07 00 4C 07 00 7E 07 00 80 00 08 08 02 33 08 02 33 01 01 01 01 07 00 5E 07 00 21 FF 00 04 00 00 00 01 07 00 08 FF 00 00 00 13 07 00 02 01 01 01 07 00 16 01 01 07 00 10 01 01 01 07 00 21 07 00 3B 07 00 4C 07 00 58 07 00 5E 07 00 4C 07 00 7E 07 00 80 00 09 08 02 33 08 02 33 01 01 01 01 07 00 5E 07 00 21 07 00 80 FF 00 05 00 00 00 01 07 00 08 FF 00 00 00 13 07 00 02 01 01 01 07 00 16 01 01 07 00 10 01 01 01 07 00 21 07 00 3B 07 00 4C 07 00 58 07 00 5E 07 00 4C 07 00 7E 07 00 80 00 09 08 02 33 08 02 33 01 01 01 01 07 00 5E 07 00 21 07 00 56 FF 00 05 00 13 07 00 02 01 01 01 07 00 16 01 01 07 00 10 01 01 01 07 00 21 07 00 3B 07 00 4C 07 00 58 07 00 5E 07 00 4C 07 00 7E 07 00 80 00 09 08 02 33 08 02 33 01 01 01 01 07 00 5E 07 00 21 07 00 92 FF 00 02 00 13 07 00 02 01 01 01 07 00 16 01 01 07 00 10 01 01 01 07 00 21 07 00 3B 07 00 4C 07 00 58 07 00 5E 07 00 4C 07 00 7E 07 00 80 00 09 08 02 33 08 02 33 01 01 01 01 07 00 5E 07 00 21 07 00 92 FF 00 02 00 00 00 01 07 00 08 FF 00 00 00 13 07 00 02 01 01 01 07 00 16 01 01 07 00 10 01 01 01 07 00 21 07 00 3B 07 00 4C 07 00 58 07 00 5E 07 00 4C 07 00 7E 07 00 80 00 09 08 02 33 08 02 33 01 01 01 01 07 00 5E 07 00 21 07 00 92 FF 00 05 00 00 00 01 07 00 08 FF 00 00 00 13 07 00 02 01 01 01 07 00 16 01 01 07 00 10 01 01 01 07 00 21 07 00 3B 07 00 4C 07 00 58 07 00 5E 07 00 4C 07 00 7E 07 00 80 00 09 08 02 33 08 02 33 01 01 01 01 07 00 5E 07 00 21 01 FF 00 03 00 00 00 01 07 00 08 FF 00 00 00 13 07 00 02 01 01 01 07 00 16 01 01 07 00 10 01 01 01 07 00 21 07 00 3B 07 00 4C 07 00 58 07 00 5E 07 00 4C 07 00 7E 07 00 80 00 0A 08 02 33 08 02 33 01 01 01 01 07 00 5E 07 00 21 01 05 FF 00 05 00 00 00 01 07 00 08 FF 00 00 00 13 07 00 02 01 01 01 07 00 16 01 01 07 00 10 01 01 01 07 00 21 07 00 3B 07 00 4C 07 00 58 07 00 5E 07 00 4C 07 00 7E 07 00 80 00 01 07 00 82 FF 00 0F 00 00 00 01 07 00 08 FF 00 00 00 14 07 00 02 01 01 01 07 00 16 01 01 07 00 10 01 01 01 07 00 21 07 00 3B 07 00 4C 07 00 58 07 00 5E 07 00 4C 07 00 7E 07 00 80 07 00 82 00 06 07 00 82 08 02 91 08 02 91 07 00 02 07 00 58 07 00 80 FF 00 05 00 00 00 01 07 00 08 FF 00 00 00 14 07 00 02 01 01 01 07 00 16 01 01 07 00 10 01 01 01 07 00 21 07 00 3B 07 00 4C 07 00 58 07 00 5E 07 00 4C 07 00 7E 07 00 80 07 00 82 00 02 07 00 82 07 00 9A FF 00 02 00 00 00 01 07 00 08 FF 00 00 00 14 07 00 02 01 01 01 07 00 16 01 01 07 00 10 01 01 01 07 00 21 07 00 3B 07 00 4C 07 00 58 07 00 5E 07 00 4C 07 00 7E 07 00 80 07 00 82 00 02 07 00 82 07 00 9A FF 00 05 00 00 00 01 07 00 08 FF 00 00 00 14 07 00 02 01 01 01 07 00 16 01 01 07 00 10 01 01 01 07 00 21 07 00 3B 07 00 4C 07 00 58 07 00 5E 07 00 4C 07 00 7E 07 00 80 07 00 82 00 00 44 07 00 5E 42 07 00 5E FF 00 04 00 00 00 01 07 00 08 FF 00 00 00 14 07 00 02 01 01 01 07 00 16 01 01 07 00 10 01 01 01 07 00 21 07 00 3B 07 00 4C 07 00 58 07 00 5E 07 00 4C 07 00 7E 07 00 80 07 00 82 00 02 07 00 5E 07 00 82 FF 00 05 00 00 00 01 07 00 08 FF 00 00 00 14 07 00 02 01 01 01 07 00 16 01 01 07 00 10 01 01 01 07 00 21 07 00 3B 07 00 4C 07 00 58 07 00 5E 07 00 4C 07 00 7E 07 00 80 07 00 82 00 00 F9 00 02 0A 02 FF 00 0F 00 13 07 00 02 01 01 01 07 00 16 01 01 07 00 10 01 01 01 07 00 21 07 00 3B 07 00 4C 07 00 58 07 00 5E 07 00 4C 07 00 7E 07 00 A7 00 03 08 02 DD 08 02 DD 07 00 A7 FF 00 02 00 13 07 00 02 01 01 01 07 00 16 01 01 07 00 10 01 01 01 07 00 21 07 00 3B 07 00 4C 07 00 58 07 00 5E 07 00 4C 07 00 7E 07 00 A7 00 03 08 02 DD 08 02 DD 07 00 A7 FF 00 02 00 00 00 01 07 00 08 FF 00 00 00 13 07 00 02 01 01 01 07 00 16 01 01 07 00 10 01 01 01 07 00 21 07 00 3B 07 00 4C 07 00 58 07 00 5E 07 00 4C 07 00 7E 07 00 A7 00 03 08 02 DD 08 02 DD 07 00 A7 FF 00 05 00 00 00 01 07 00 08 FF 00 00 00 13 07 00 02 01 01 01 07 00 16 01 01 07 00 10 01 01 01 07 00 21 07 00 3B 07 00 4C 07 00 58 07 00 5E 07 00 4C 07 00 7E 07 00 A7 00 03 08 02 DD 08 02 DD 03 FF 00 02 00 00 00 01 07 00 08 FF 00 00 00 13 07 00 02 01 01 01 07 00 16 01 01 07 00 10 01 01 01 07 00 21 07 00 3B 07 00 4C 07 00 58 07 00 5E 07 00 4C 07 00 7E 07 00 A7 00 03 08 02 DD 08 02 DD 03 FF 00 05 00 00 00 01 07 00 08 FF 00 00 00 13 07 00 02 01 01 01 07 00 16 01 01 07 00 10 01 01 01 07 00 21 07 00 3B 07 00 4C 07 00 58 07 00 5E 07 00 4C 07 00 7E 07 00 A7 00 03 08 02 DD 08 02 DD 07 00 AF FF 00 04 00 00 00 01 07 00 08 FF 00 00 00 13 07 00 02 01 01 01 07 00 16 01 01 07 00 10 01 01 01 07 00 21 07 00 3B 07 00 4C 07 00 58 07 00 5E 07 00 4C 07 00 7E 07 00 A7 00 04 08 02 DD 08 02 DD 07 00 AF 07 00 A7 FF 00 05 00 00 00 01 07 00 08 FF 00 00 00 13 07 00 02 01 01 01 07 00 16 01 01 07 00 10 01 01 01 07 00 21 07 00 3B 07 00 4C 07 00 58 07 00 5E 07 00 4C 07 00 7E 07 00 A7 00 04 08 02 DD 08 02 DD 07 00 AF 03 FF 00 02 00 00 00 01 07 00 08 FF 00 00 00 13 07 00 02 01 01 01 07 00 16 01 01 07 00 10 01 01 01 07 00 21 07 00 3B 07 00 4C 07 00 58 07 00 5E 07 00 4C 07 00 7E 07 00 A7 00 04 08 02 DD 08 02 DD 07 00 AF 03 FF 00 05 00 00 00 01 07 00 08 FF 00 00 00 13 07 00 02 01 01 01 07 00 16 01 01 07 00 10 01 01 01 07 00 21 07 00 3B 07 00 4C 07 00 58 07 00 5E 07 00 4C 07 00 7E 07 00 A7 00 04 08 02 DD 08 02 DD 07 00 AF 07 00 AF FF 00 04 00 00 00 01 07 00 08 FF 00 00 00 13 07 00 02 01 01 01 07 00 16 01 01 07 00 10 01 01 01 07 00 21 07 00 3B 07 00 4C 07 00 58 07 00 5E 07 00 4C 07 00 7E 07 00 A7 00 05 08 02 DD 08 02 DD 07 00 AF 07 00 AF 07 00 A7 FF 00 05 00 00 00 01 07 00 08 FF 00 00 00 13 07 00 02 01 01 01 07 00 16 01 01 07 00 10 01 01 01 07 00 21 07 00 3B 07 00 4C 07 00 58 07 00 5E 07 00 4C 07 00 7E 07 00 A7 00 05 08 02 DD 08 02 DD 07 00 AF 07 00 AF 07 00 AF FF 00 06 00 00 00 01 07 00 08 FF 00 00 00 13 07 00 02 01 01 01 07 00 16 01 01 07 00 10 01 01 01 07 00 21 07 00 3B 07 00 4C 07 00 58 07 00 5E 07 00 4C 07 00 7E 07 00 A7 00 07 08 02 DD 08 02 DD 07 00 AF 07 00 AF 07 00 AF 07 00 5E 07 00 A7 FF 00 05 00 00 00 01 07 00 08 FF 00 00 00 13 07 00 02 01 01 01 07 00 16 01 01 07 00 10 01 01 01 07 00 21 07 00 3B 07 00 4C 07 00 58 07 00 5E 07 00 4C 07 00 7E 07 00 A7 00 07 08 02 DD 08 02 DD 07 00 AF 07 00 AF 07 00 AF 07 00 5E 07 00 21 FF 00 02 00 00 00 01 07 00 08 FF 00 00 00 13 07 00 02 01 01 01 07 00 16 01 01 07 00 10 01 01 01 07 00 21 07 00 3B 07 00 4C 07 00 58 07 00 5E 07 00 4C 07 00 7E 07 00 A7 00 07 08 02 DD 08 02 DD 07 00 AF 07 00 AF 07 00 AF 07 00 5E 07 00 21 FF 00 05 00 00 00 01 07 00 08 FF 00 00 00 13 07 00 02 01 01 01 07 00 16 01 01 07 00 10 01 01 01 07 00 21 07 00 3B 07 00 4C 07 00 58 07 00 5E 07 00 4C 07 00 7E 07 00 A7 00 01 07 00 A9 FF 00 0B 00 14 07 00 02 01 01 01 07 00 16 01 01 07 00 10 01 01 01 07 00 21 07 00 3B 07 00 4C 07 00 58 07 00 5E 07 00 4C 07 00 7E 07 00 A7 07 00 A9 00 04 07 00 A9 08 03 42 08 03 42 07 00 02 FF 00 02 00 14 07 00 02 01 01 01 07 00 16 01 01 07 00 10 01 01 01 07 00 21 07 00 3B 07 00 4C 07 00 58 07 00 5E 07 00 4C 07 00 7E 07 00 A7 07 00 A9 00 04 07 00 A9 08 03 42 08 03 42 07 00 02 FF 00 06 00 00 00 01 07 00 08 FF 00 00 00 14 07 00 02 01 01 01 07 00 16 01 01 07 00 10 01 01 01 07 00 21 07 00 3B 07 00 4C 07 00 58 07 00 5E 07 00 4C 07 00 7E 07 00 A7 07 00 A9 00 06 07 00 A9 08 03 42 08 03 42 07 00 02 07 00 58 07 00 7E FF 00 05 00 00 00 01 07 00 08 FF 00 00 00 14 07 00 02 01 01 01 07 00 16 01 01 07 00 10 01 01 01 07 00 21 07 00 3B 07 00 4C 07 00 58 07 00 5E 07 00 4C 07 00 7E 07 00 A7 07 00 A9 00 02 07 00 A9 07 00 BF FF 00 02 00 00 00 01 07 00 08 FF 00 00 00 14 07 00 02 01 01 01 07 00 16 01 01 07 00 10 01 01 01 07 00 21 07 00 3B 07 00 4C 07 00 58 07 00 5E 07 00 4C 07 00 7E 07 00 A7 07 00 A9 00 02 07 00 A9 07 00 BF FF 00 05 00 00 00 01 07 00 08 FF 00 00 00 14 07 00 02 01 01 01 07 00 16 01 01 07 00 10 01 01 01 07 00 21 07 00 3B 07 00 4C 07 00 58 07 00 5E 07 00 4C 07 00 7E 07 00 A7 07 00 A9 00 00 FF 00 06 00 00 00 01 07 00 08 FF 00 00 00 14 07 00 02 01 01 01 07 00 16 01 01 07 00 10 01 01 01 07 00 21 07 00 3B 07 00 4C 07 00 58 07 00 5E 07 00 4C 07 00 7E 07 00 A7 07 00 A9 00 02 07 00 5E 07 00 A9 FF 00 05 00 00 00 01 07 00 08 FF 00 00 00 14 07 00 02 01 01 01 07 00 16 01 01 07 00 10 01 01 01 07 00 21 07 00 3B 07 00 4C 07 00 58 07 00 5E 07 00 4C 07 00 7E 07 00 A7 07 00 A9 00 00 F9 00 02 02 02 FF 00 17 00 00 00 01 07 00 08 FF 00 00 00 13 07 00 02 01 01 01 07 00 16 01 01 07 00 10 01 01 01 07 00 21 07 00 3B 07 00 4C 07 00 58 07 00 5E 07 00 4C 07 00 7E 07 00 C8 00 03 08 03 8E 08 03 8E 07 00 C8 FF 00 05 00 00 00 01 07 00 08 FF 00 00 00 13 07 00 02 01 01 01 07 00 16 01 01 07 00 10 01 01 01 07 00 21 07 00 3B 07 00 4C 07 00 58 07 00 5E 07 00 4C 07 00 7E 07 00 C8 00 03 08 03 8E 08 03 8E 01 FF 00 02 00 00 00 01 07 00 08 FF 00 00 00 13 07 00 02 01 01 01 07 00 16 01 01 07 00 10 01 01 01 07 00 21 07 00 3B 07 00 4C 07 00 58 07 00 5E 07 00 4C 07 00 7E 07 00 C8 00 03 08 03 8E 08 03 8E 01 FF 00 05 00 00 00 01 07 00 08 FF 00 00 00 13 07 00 02 01 01 01 07 00 16 01 01 07 00 10 01 01 01 07 00 21 07 00 3B 07 00 4C 07 00 58 07 00 5E 07 00 4C 07 00 7E 07 00 C8 00 03 08 03 8E 08 03 8E 07 00 CC FF 00 04 00 00 00 01 07 00 08 FF 00 00 00 13 07 00 02 01 01 01 07 00 16 01 01 07 00 10 01 01 01 07 00 21 07 00 3B 07 00 4C 07 00 58 07 00 5E 07 00 4C 07 00 7E 07 00 C8 00 04 08 03 8E 08 03 8E 07 00 CC 07 00 C8 FF 00 05 00 00 00 01 07 00 08 FF 00 00 00 13 07 00 02 01 01 01 07 00 16 01 01 07 00 10 01 01 01 07 00 21 07 00 3B 07 00 4C 07 00 58 07 00 5E 07 00 4C 07 00 7E 07 00 C8 00 04 08 03 8E 08 03 8E 07 00 CC 01 FF 00 02 00 00 00 01 07 00 08 FF 00 00 00 13 07 00 02 01 01 01 07 00 16 01 01 07 00 10 01 01 01 07 00 21 07 00 3B 07 00 4C 07 00 58 07 00 5E 07 00 4C 07 00 7E 07 00 C8 00 04 08 03 8E 08 03 8E 07 00 CC 01 FF 00 05 00 00 00 01 07 00 08 FF 00 00 00 13 07 00 02 01 01 01 07 00 16 01 01 07 00 10 01 01 01 07 00 21 07 00 3B 07 00 4C 07 00 58 07 00 5E 07 00 4C 07 00 7E 07 00 C8 00 04 08 03 8E 08 03 8E 07 00 CC 07 00 CC FF 00 04 00 00 00 01 07 00 08 FF 00 00 00 13 07 00 02 01 01 01 07 00 16 01 01 07 00 10 01 01 01 07 00 21 07 00 3B 07 00 4C 07 00 58 07 00 5E 07 00 4C 07 00 7E 07 00 C8 00 05 08 03 8E 08 03 8E 07 00 CC 07 00 CC 07 00 C8 FF 00 05 00 00 00 01 07 00 08 FF 00 00 00 13 07 00 02 01 01 01 07 00 16 01 01 07 00 10 01 01 01 07 00 21 07 00 3B 07 00 4C 07 00 58 07 00 5E 07 00 4C 07 00 7E 07 00 C8 00 05 08 03 8E 08 03 8E 07 00 CC 07 00 CC 07 00 CC FF 00 06 00 00 00 01 07 00 08 FF 00 00 00 13 07 00 02 01 01 01 07 00 16 01 01 07 00 10 01 01 01 07 00 21 07 00 3B 07 00 4C 07 00 58 07 00 5E 07 00 4C 07 00 7E 07 00 C8 00 07 08 03 8E 08 03 8E 07 00 CC 07 00 CC 07 00 CC 07 00 5E 07 00 C8 FF 00 05 00 00 00 01 07 00 08 FF 00 00 00 13 07 00 02 01 01 01 07 00 16 01 01 07 00 10 01 01 01 07 00 21 07 00 3B 07 00 4C 07 00 58 07 00 5E 07 00 4C 07 00 7E 07 00 C8 00 07 08 03 8E 08 03 8E 07 00 CC 07 00 CC 07 00 CC 07 00 5E 07 00 21 FF 00 02 00 13 07 00 02 01 01 01 07 00 16 01 01 07 00 10 01 01 01 07 00 21 07 00 3B 07 00 4C 07 00 58 07 00 5E 07 00 4C 07 00 7E 07 00 C8 00 07 08 03 8E 08 03 8E 07 00 CC 07 00 CC 07 00 CC 07 00 5E 07 00 21 FF 00 02 00 13 07 00 02 01 01 01 07 00 16 01 01 07 00 10 01 01 01 07 00 21 07 00 3B 07 00 4C 07 00 58 07 00 5E 07 00 4C 07 00 7E 07 00 C8 00 07 08 03 8E 08 03 8E 07 00 CC 07 00 CC 07 00 CC 07 00 5E 07 00 21 FF 00 02 00 00 00 01 07 00 08 FF 00 00 00 13 07 00 02 01 01 01 07 00 16 01 01 07 00 10 01 01 01 07 00 21 07 00 3B 07 00 4C 07 00 58 07 00 5E 07 00 4C 07 00 7E 07 00 C8 00 07 08 03 8E 08 03 8E 07 00 CC 07 00 CC 07 00 CC 07 00 5E 07 00 21 FF 00 05 00 00 00 01 07 00 08 FF 00 00 00 13 07 00 02 01 01 01 07 00 16 01 01 07 00 10 01 01 01 07 00 21 07 00 3B 07 00 4C 07 00 58 07 00 5E 07 00 4C 07 00 7E 07 00 C8 00 01 07 00 A9 FC 00 04 07 00 A9 02 FF 00 0D 00 00 00 01 07 00 08 FF 00 00 00 14 07 00 02 01 01 01 07 00 16 01 01 07 00 10 01 01 01 07 00 21 07 00 3B 07 00 4C 07 00 58 07 00 5E 07 00 4C 07 00 7E 07 00 C8 07 00 A9 00 06 07 00 A9 08 03 F9 08 03 F9 07 00 02 07 00 58 07 00 7E FF 00 05 00 00 00 01 07 00 08 FF 00 00 00 14 07 00 02 01 01 01 07 00 16 01 01 07 00 10 01 01 01 07 00 21 07 00 3B 07 00 4C 07 00 58 07 00 5E 07 00 4C 07 00 7E 07 00 C8 07 00 A9 00 02 07 00 A9 07 00 D7 FF 00 02 00 00 00 01 07 00 08 FF 00 00 00 14 07 00 02 01 01 01 07 00 16 01 01 07 00 10 01 01 01 07 00 21 07 00 3B 07 00 4C 07 00 58 07 00 5E 07 00 4C 07 00 7E 07 00 C8 07 00 A9 00 02 07 00 A9 07 00 D7 FF 00 05 00 00 00 01 07 00 08 FF 00 00 00 14 07 00 02 01 01 01 07 00 16 01 01 07 00 10 01 01 01 07 00 21 07 00 3B 07 00 4C 07 00 58 07 00 5E 07 00 4C 07 00 7E 07 00 C8 07 00 A9 00 00 FF 00 06 00 00 00 01 07 00 08 FF 00 00 00 14 07 00 02 01 01 01 07 00 16 01 01 07 00 10 01 01 01 07 00 21 07 00 3B 07 00 4C 07 00 58 07 00 5E 07 00 4C 07 00 7E 07 00 C8 07 00 A9 00 02 07 00 5E 07 00 A9 FF 00 05 00 00 00 01 07 00 08 FF 00 00 00 14 07 00 02 01 01 01 07 00 16 01 01 07 00 10 01 01 01 07 00 21 07 00 3B 07 00 4C 07 00 58 07 00 5E 07 00 4C 07 00 7E 07 00 C8 07 00 A9 00 00 F9 00 02 FF 00 1A 00 00 00 01 07 00 08 FF 00 00 00 12 07 00 02 01 01 01 07 00 16 01 01 07 00 10 01 01 01 07 00 21 07 00 3B 07 00 4C 07 00 58 07 00 5E 07 00 4C 07 00 7E 00 08 08 04 32 08 04 32 01 01 01 01 07 00 3B 07 00 7E FF 00 05 00 00 00 01 07 00 08 FF 00 00 00 12 07 00 02 01 01 01 07 00 16 01 01 07 00 10 01 01 01 07 00 21 07 00 3B 07 00 4C 07 00 58 07 00 5E 07 00 4C 07 00 7E 00 08 08 04 32 08 04 32 01 01 01 01 07 00 3B 07 00 21 FF 00 02 00 00 00 01 07 00 08 FF 00 00 00 12 07 00 02 01 01 01 07 00 16 01 01 07 00 10 01 01 01 07 00 21 07 00 3B 07 00 4C 07 00 58 07 00 5E 07 00 4C 07 00 7E 00 08 08 04 32 08 04 32 01 01 01 01 07 00 3B 07 00 21 FF 00 05 00 00 00 01 07 00 08 FF 00 00 00 12 07 00 02 01 01 01 07 00 16 01 01 07 00 10 01 01 01 07 00 21 07 00 3B 07 00 4C 07 00 58 07 00 5E 07 00 4C 07 00 7E 00 01 07 00 DC FF 00 0D 00 00 00 01 07 00 08 FF 00 00 00 14 07 00 02 01 01 01 07 00 16 01 01 07 00 10 01 01 01 07 00 21 07 00 3B 07 00 4C 07 00 58 07 00 5E 07 00 4C 07 00 7E 07 00 DC 07 00 DA 00 01 07 00 DA FF 00 05 00 00 00 01 07 00 08 FF 00 00 00 14 07 00 02 01 01 01 07 00 16 01 01 07 00 10 01 01 01 07 00 21 07 00 3B 07 00 4C 07 00 58 07 00 5E 07 00 4C 07 00 7E 07 00 DC 07 00 DA 00 01 07 00 E6 FF 00 07 00 15 07 00 02 01 01 01 07 00 16 01 01 07 00 10 01 01 01 07 00 21 07 00 3B 07 00 4C 07 00 58 07 00 5E 07 00 4C 07 00 7E 07 00 DC 07 00 DA 07 00 E6 00 01 01 42 01 FD 00 04 01 01 FF 00 18 00 00 00 01 07 00 08 FF 00 00 00 18 07 00 02 01 01 01 07 00 16 01 01 07 00 10 01 01 01 07 00 21 07 00 3B 07 00 4C 07 00 58 07 00 5E 07 00 4C 07 00 7E 07 00 DC 07 00 DA 07 00 E6 01 01 07 00 E8 00 05 08 04 8C 08 04 8C 01 01 07 00 5E FF 00 05 00 00 00 01 07 00 08 FF 00 00 00 18 07 00 02 01 01 01 07 00 16 01 01 07 00 10 01 01 01 07 00 21 07 00 3B 07 00 4C 07 00 58 07 00 5E 07 00 4C 07 00 7E 07 00 DC 07 00 DA 07 00 E6 01 01 07 00 E8 00 05 08 04 8C 08 04 8C 01 01 07 00 88 FF 00 0B 00 00 00 01 07 00 08 FF 00 00 00 18 07 00 02 01 01 01 07 00 16 01 01 07 00 10 01 01 01 07 00 21 07 00 3B 07 00 4C 07 00 58 07 00 5E 07 00 4C 07 00 7E 07 00 DC 07 00 DA 07 00 E6 01 01 07 00 E8 00 08 08 04 8C 08 04 8C 01 01 01 01 07 00 5E 07 00 E8 FF 00 05 00 00 00 01 07 00 08 FF 00 00 00 18 07 00 02 01 01 01 07 00 16 01 01 07 00 10 01 01 01 07 00 21 07 00 3B 07 00 4C 07 00 58 07 00 5E 07 00 4C 07 00 7E 07 00 DC 07 00 DA 07 00 E6 01 01 07 00 E8 00 08 08 04 8C 08 04 8C 01 01 01 01 07 00 5E 07 00 21 FF 00 04 00 00 00 01 07 00 08 FF 00 00 00 18 07 00 02 01 01 01 07 00 16 01 01 07 00 10 01 01 01 07 00 21 07 00 3B 07 00 4C 07 00 58 07 00 5E 07 00 4C 07 00 7E 07 00 DC 07 00 DA 07 00 E6 01 01 07 00 E8 00 09 08 04 8C 08 04 8C 01 01 01 01 07 00 5E 07 00 21 07 00 E8 FF 00 05 00 00 00 01 07 00 08 FF 00 00 00 18 07 00 02 01 01 01 07 00 16 01 01 07 00 10 01 01 01 07 00 21 07 00 3B 07 00 4C 07 00 58 07 00 5E 07 00 4C 07 00 7E 07 00 DC 07 00 DA 07 00 E6 01 01 07 00 E8 00 09 08 04 8C 08 04 8C 01 01 01 01 07 00 5E 07 00 21 01 FF 00 04 00 00 00 01 07 00 08 FF 00 00 00 18 07 00 02 01 01 01 07 00 16 01 01 07 00 10 01 01 01 07 00 21 07 00 3B 07 00 4C 07 00 58 07 00 5E 07 00 4C 07 00 7E 07 00 DC 07 00 DA 07 00 E6 01 01 07 00 E8 00 0A 08 04 8C 08 04 8C 01 01 01 01 07 00 5E 07 00 21 01 07 00 DA FF 00 05 00 00 00 01 07 00 08 FF 00 00 00 18 07 00 02 01 01 01 07 00 16 01 01 07 00 10 01 01 01 07 00 21 07 00 3B 07 00 4C 07 00 58 07 00 5E 07 00 4C 07 00 7E 07 00 DC 07 00 DA 07 00 E6 01 01 07 00 E8 00 01 07 00 82 FC 00 04 07 00 82 02 FF 00 0D 00 00 00 01 07 00 08 FF 00 00 00 19 07 00 02 01 01 01 07 00 16 01 01 07 00 10 01 01 01 07 00 21 07 00 3B 07 00 4C 07 00 58 07 00 5E 07 00 4C 07 00 7E 07 00 DC 07 00 DA 07 00 E6 01 01 07 00 E8 07 00 82 00 06 07 00 82 08 04 D7 08 04 D7 07 00 02 07 00 DA 07 00 E8 FF 00 05 00 00 00 01 07 00 08 FF 00 00 00 19 07 00 02 01 01 01 07 00 16 01 01 07 00 10 01 01 01 07 00 21 07 00 3B 07 00 4C 07 00 58 07 00 5E 07 00 4C 07 00 7E 07 00 DC 07 00 DA 07 00 E6 01 01 07 00 E8 07 00 82 00 02 07 00 82 07 00 EC FF 00 02 00 00 00 01 07 00 08 FF 00 00 00 19 07 00 02 01 01 01 07 00 16 01 01 07 00 10 01 01 01 07 00 21 07 00 3B 07 00 4C 07 00 58 07 00 5E 07 00 4C 07 00 7E 07 00 DC 07 00 DA 07 00 E6 01 01 07 00 E8 07 00 82 00 02 07 00 82 07 00 EC FF 00 05 00 00 00 01 07 00 08 FF 00 00 00 19 07 00 02 01 01 01 07 00 16 01 01 07 00 10 01 01 01 07 00 21 07 00 3B 07 00 4C 07 00 58 07 00 5E 07 00 4C 07 00 7E 07 00 DC 07 00 DA 07 00 E6 01 01 07 00 E8 07 00 82 00 00 FF 00 06 00 00 00 01 07 00 08 FF 00 00 00 19 07 00 02 01 01 01 07 00 16 01 01 07 00 10 01 01 01 07 00 21 07 00 3B 07 00 4C 07 00 58 07 00 5E 07 00 4C 07 00 7E 07 00 DC 07 00 DA 07 00 E6 01 01 07 00 E8 07 00 82 00 02 07 00 DC 07 00 82 FF 00 05 00 00 00 01 07 00 08 FF 00 00 00 19 07 00 02 01 01 01 07 00 16 01 01 07 00 10 01 01 01 07 00 21 07 00 3B 07 00 4C 07 00 58 07 00 5E 07 00 4C 07 00 7E 07 00 DC 07 00 DA 07 00 E6 01 01 07 00 E8 07 00 82 00 00 F9 00 05 FF 00 06 00 00 00 01 07 00 08 FF 00 00 00 17 07 00 02 01 01 01 07 00 16 01 01 07 00 10 01 01 01 07 00 21 07 00 3B 07 00 4C 07 00 58 07 00 5E 07 00 4C 07 00 7E 07 00 DC 07 00 DA 07 00 E6 01 01 00 02 07 00 5E 07 00 DC FF 00 05 00 00 00 01 07 00 08 FF 00 00 00 17 07 00 02 01 01 01 07 00 16 01 01 07 00 10 01 01 01 07 00 21 07 00 3B 07 00 4C 07 00 58 07 00 5E 07 00 4C 07 00 7E 07 00 DC 07 00 DA 07 00 E6 01 01 00 00 FF 00 02 00 12 07 00 02 01 01 01 07 00 16 01 01 07 00 10 01 01 01 07 00 21 07 00 3B 07 00 4C 07 00 58 07 00 5E 07 00 4C 07 00 7E 00 00 FF 00 1D 00 00 00 01 07 00 08 FF 00 00 00 13 07 00 02 01 01 01 07 00 16 01 01 07 00 10 01 01 01 07 00 21 07 00 3B 07 00 4C 07 00 58 07 00 5E 07 00 4C 07 00 7E 07 00 F2 00 07 08 05 2C 08 05 2C 01 01 01 01 07 00 F2 FF 00 05 00 00 00 01 07 00 08 FF 00 00 00 13 07 00 02 01 01 01 07 00 16 01 01 07 00 10 01 01 01 07 00 21 07 00 3B 07 00 4C 07 00 58 07 00 5E 07 00 4C 07 00 7E 07 00 F2 00 07 08 05 2C 08 05 2C 01 01 01 01 07 00 56 FF 00 05 00 00 00 01 07 00 08 FF 00 00 00 13 07 00 02 01 01 01 07 00 16 01 01 07 00 10 01 01 01 07 00 21 07 00 3B 07 00 4C 07 00 58 07 00 5E 07 00 4C 07 00 7E 07 00 F2 00 07 08 05 2C 08 05 2C 01 01 01 01 07 00 CC FF 00 05 00 00 00 01 07 00 08 FF 00 00 00 13 07 00 02 01 01 01 07 00 16 01 01 07 00 10 01 01 01 07 00 21 07 00 3B 07 00 4C 07 00 58 07 00 5E 07 00 4C 07 00 7E 07 00 F2 00 07 08 05 2C 08 05 2C 01 01 01 01 01 FF 00 04 00 00 00 01 07 00 08 FF 00 00 00 13 07 00 02 01 01 01 07 00 16 01 01 07 00 10 01 01 01 07 00 21 07 00 3B 07 00 4C 07 00 58 07 00 5E 07 00 4C 07 00 7E 07 00 F2 00 08 08 05 2C 08 05 2C 01 01 01 01 01 07 00 F2 FF 00 05 00 00 00 01 07 00 08 FF 00 00 00 13 07 00 02 01 01 01 07 00 16 01 01 07 00 10 01 01 01 07 00 21 07 00 3B 07 00 4C 07 00 58 07 00 5E 07 00 4C 07 00 7E 07 00 F2 00 08 08 05 2C 08 05 2C 01 01 01 01 01 01 FF 00 06 00 13 07 00 02 01 01 01 07 00 16 01 01 07 00 10 01 01 01 07 00 21 07 00 3B 07 00 4C 07 00 58 07 00 5E 07 00 4C 07 00 7E 07 00 F2 00 0A 08 05 2C 08 05 2C 01 01 01 01 01 01 07 00 5E 07 00 F2 FF 00 02 00 13 07 00 02 01 01 01 07 00 16 01 01 07 00 10 01 01 01 07 00 21 07 00 3B 07 00 4C 07 00 58 07 00 5E 07 00 4C 07 00 7E 07 00 F2 00 0A 08 05 2C 08 05 2C 01 01 01 01 01 01 07 00 5E 07 00 F2 FF 00 02 00 00 00 01 07 00 08 FF 00 00 00 13 07 00 02 01 01 01 07 00 16 01 01 07 00 10 01 01 01 07 00 21 07 00 3B 07 00 4C 07 00 58 07 00 5E 07 00 4C 07 00 7E 07 00 F2 00 0A 08 05 2C 08 05 2C 01 01 01 01 01 01 07 00 5E 07 00 F2 FF 00 05 00 00 00 01 07 00 08 FF 00 00 00 13 07 00 02 01 01 01 07 00 16 01 01 07 00 10 01 01 01 07 00 21 07 00 3B 07 00 4C 07 00 58 07 00 5E 07 00 4C 07 00 7E 07 00 F2 00 0A 08 05 2C 08 05 2C 01 01 01 01 01 01 07 00 5E 07 00 21 FF 00 04 00 13 07 00 02 01 01 01 07 00 16 01 01 07 00 10 01 01 01 07 00 21 07 00 3B 07 00 4C 07 00 58 07 00 5E 07 00 4C 07 00 7E 07 00 F2 00 0B 08 05 2C 08 05 2C 01 01 01 01 01 01 07 00 5E 07 00 21 07 00 F2 FF 00 02 00 13 07 00 02 01 01 01 07 00 16 01 01 07 00 10 01 01 01 07 00 21 07 00 3B 07 00 4C 07 00 58 07 00 5E 07 00 4C 07 00 7E 07 00 F2 00 0B 08 05 2C 08 05 2C 01 01 01 01 01 01 07 00 5E 07 00 21 07 00 F2 FF 00 02 00 00 00 01 07 00 08 FF 00 00 00 13 07 00 02 01 01 01 07 00 16 01 01 07 00 10 01 01 01 07 00 21 07 00 3B 07 00 4C 07 00 58 07 00 5E 07 00 4C 07 00 7E 07 00 F2 00 0B 08 05 2C 08 05 2C 01 01 01 01 01 01 07 00 5E 07 00 21 07 00 F2 FF 00 05 00 00 00 01 07 00 08 FF 00 00 00 13 07 00 02 01 01 01 07 00 16 01 01 07 00 10 01 01 01 07 00 21 07 00 3B 07 00 4C 07 00 58 07 00 5E 07 00 4C 07 00 7E 07 00 F2 00 01 07 00 F4 FF 00 0D 00 00 00 01 07 00 08 FF 00 00 00 14 07 00 02 01 01 01 07 00 16 01 01 07 00 10 01 01 01 07 00 21 07 00 3B 07 00 4C 07 00 58 07 00 5E 07 00 4C 07 00 7E 07 00 F2 07 00 F4 00 05 07 00 F4 08 05 8A 08 05 8A 07 00 02 07 00 7E FF 00 05 00 00 00 01 07 00 08 FF 00 00 00 14 07 00 02 01 01 01 07 00 16 01 01 07 00 10 01 01 01 07 00 21 07 00 3B 07 00 4C 07 00 58 07 00 5E 07 00 4C 07 00 7E 07 00 F2 07 00 F4 00 02 07 00 F4 07 01 01 FF 00 02 00 00 00 01 07 00 08 FF 00 00 00 14 07 00 02 01 01 01 07 00 16 01 01 07 00 10 01 01 01 07 00 21 07 00 3B 07 00 4C 07 00 58 07 00 5E 07 00 4C 07 00 7E 07 00 F2 07 00 F4 00 02 07 00 F4 07 01 01 FF 00 05 00 00 00 01 07 00 08 FF 00 00 00 14 07 00 02 01 01 01 07 00 16 01 01 07 00 10 01 01 01 07 00 21 07 00 3B 07 00 4C 07 00 58 07 00 5E 07 00 4C 07 00 7E 07 00 F2 07 00 F4 00 00 FF 00 06 00 00 00 01 07 00 08 FF 00 00 00 14 07 00 02 01 01 01 07 00 16 01 01 07 00 10 01 01 01 07 00 21 07 00 3B 07 00 4C 07 00 58 07 00 5E 07 00 4C 07 00 7E 07 00 F2 07 00 F4 00 02 07 00 5E 07 00 F4 FF 00 05 00 00 00 01 07 00 08 FF 00 00 00 12 07 00 02 01 01 01 07 00 16 01 01 07 00 10 01 01 01 07 00 21 07 00 3B 07 00 4C 07 00 58 07 00 5E 07 00 4C 07 00 7E 00 00 F9 00 02 FF 00 0C 00 10 07 00 02 01 01 01 07 00 16 01 01 07 00 10 01 01 01 07 00 21 07 00 3B 07 00 4C 07 00 58 07 00 5E 00 06 08 05 B9 08 05 B9 01 01 01 01 FF 00 02 00 10 07 00 02 01 01 01 07 00 16 01 01 07 00 10 01 01 01 07 00 21 07 00 3B 07 00 4C 07 00 58 07 00 5E 00 06 08 05 B9 08 05 B9 01 01 01 01 FF 00 04 00 10 07 00 02 01 01 01 07 00 16 01 01 07 00 10 01 01 01 07 00 21 07 00 3B 07 00 4C 07 00 58 07 00 5E 00 07 08 05 B9 08 05 B9 01 01 01 01 07 00 5E FF 00 02 00 10 07 00 02 01 01 01 07 00 16 01 01 07 00 10 01 01 01 07 00 21 07 00 3B 07 00 4C 07 00 58 07 00 5E 00 07 08 05 B9 08 05 B9 01 01 01 01 07 00 5E FF 00 04 00 00 00 01 07 00 08 FF 00 00 00 10 07 00 02 01 01 01 07 00 16 01 01 07 00 10 01 01 01 07 00 21 07 00 3B 07 00 4C 07 00 58 07 00 5E 00 08 08 05 B9 08 05 B9 01 01 01 01 07 00 5E 07 00 58 FF 00 05 00 00 00 01 07 00 08 FF 00 00 00 10 07 00 02 01 01 01 07 00 16 01 01 07 00 10 01 01 01 07 00 21 07 00 3B 07 00 4C 07 00 58 07 00 5E 00 01 07 01 09 FF 00 08 00 00 00 01 07 00 08 FF 00 00 00 11 07 00 02 01 01 01 07 00 16 01 01 07 00 10 01 01 01 07 00 21 07 00 3B 07 00 4C 07 00 58 07 00 5E 07 01 09 00 02 07 00 5E 07 01 09 FF 00 05 00 00 00 01 07 00 08 FF 00 00 00 11 07 00 02 01 01 01 07 00 16 01 01 07 00 10 01 01 01 07 00 21 07 00 3B 07 00 4C 07 00 58 07 00 5E 07 01 09 00 00 02 02 FF 00 06 00 00 00 01 07 00 08 FF 00 00 00 11 07 00 02 01 01 01 07 00 16 01 01 07 00 10 01 01 01 07 00 21 07 00 3B 07 00 4C 07 00 58 07 00 5E 07 01 09 00 02 07 00 3B 07 00 5E FF 00 05 00 00 00 01 07 00 08 FF 00 00 00 11 07 00 02 01 01 01 07 00 16 01 01 07 00 10 01 01 01 07 00 21 07 00 3B 07 00 4C 07 00 58 07 00 5E 07 01 09 00 00 F9 00 02 FA 00 02 14 05 FF 00 05 00 00 00 01 07 00 08 FF 00 00 00 0E 07 00 02 01 01 01 07 00 16 01 01 07 00 10 01 01 01 07 00 21 07 00 3B 07 00 4C 00 02 07 00 3B 01 FF 00 05 00 00 00 01 07 00 08 FF 00 00 00 0E 07 00 02 01 01 01 07 00 16 01 01 07 00 10 01 01 01 07 00 21 07 00 3B 07 00 4C 00 00 FF 00 05 00 00 00 01 07 00 08 FF 00 00 00 0E 07 00 02 01 01 01 07 00 16 01 01 07 00 10 01 01 01 07 00 21 07 00 3B 07 00 4C 00 02 07 00 3B 01 FF 00 05 00 00 00 01 07 00 08 FF 00 00 00 0E 07 00 02 01 01 01 07 00 16 01 01 07 00 10 01 01 01 07 00 21 07 00 3B 07 00 4C 00 00 0A 02 FF 00 05 00 00 00 01 07 00 08 FF 00 00 00 0E 07 00 02 01 01 01 07 00 16 01 01 07 00 10 01 01 01 07 00 21 07 00 3B 07 00 4C 00 02 07 00 02 07 00 3B FF 00 05 00 00 00 01 07 00 08 FF 00 00 00 0E 07 00 02 01 01 01 07 00 16 01 01 07 00 10 01 01 01 07 00 21 07 00 3B 07 00 4C 00 00 FF 00 05 00 07 07 00 02 01 01 01 07 00 16 01 01 00 00 FF 00 05 00 00 00 01 07 00 08 FF 00 00 00 07 07 00 02 01 01 01 07 00 16 01 01 00 01 07 01 23 FF 00 05 00 00 00 01 07 00 08 FF 00 00 00 07 07 00 02 01 01 01 07 00 16 01 01 00 01 01 FF 00 05 00 00 00 01 07 00 08 FF 00 00 00 07 07 00 02 01 01 01 07 00 16 01 01 00 00 FF 00 05 00 00 00 01 07 00 08 FF 00 00 00 07 07 00 02 01 01 01 07 00 16 01 01 00 00 02 FF 00 02 00 00 00 01 07 00 08 FF 00 00 00 07 07 00 02 01 01 01 07 00 16 01 01 00 00 FF 00 05 00 00 00 01 07 00 08 FF 00 00 00 07 07 00 02 01 01 01 07 00 16 01 01 00 00 FF 00 00 00 00 00 01 07 00 08 41 07 00 08 41 07 00 08 41 07 00 08 41 07 00 08 41 07 00 08 41 07 00 08 41 07 00 08 41 07 00 08 41 07 00 08 41 07 00 08 41 07 00 08 41 07 00 08 41 07 00 08 41 07 00 08 41 07 00 08 41 07 00 08 41 07 00 08 41 07 00 08 41 07 00 08 41 07 00 08 41 07 00 08 41 07 00 08 41 07 00 08
        // 
        // The error that occurred was:
        // 
        // java.lang.NullPointerException
        //     at com.strobel.decompiler.languages.java.ast.AstBuilder.convertType(AstBuilder.java:344)
        //     at com.strobel.decompiler.languages.java.ast.AstBuilder.convertType(AstBuilder.java:173)
        //     at com.strobel.decompiler.languages.java.ast.AstMethodBodyBuilder.transformCall(AstMethodBodyBuilder.java:1119)
        //     at com.strobel.decompiler.languages.java.ast.AstMethodBodyBuilder.transformByteCode(AstMethodBodyBuilder.java:1009)
        //     at com.strobel.decompiler.languages.java.ast.AstMethodBodyBuilder.transformExpression(AstMethodBodyBuilder.java:540)
        //     at com.strobel.decompiler.languages.java.ast.AstMethodBodyBuilder.transformByteCode(AstMethodBodyBuilder.java:554)
        //     at com.strobel.decompiler.languages.java.ast.AstMethodBodyBuilder.transformExpression(AstMethodBodyBuilder.java:540)
        //     at com.strobel.decompiler.languages.java.ast.AstMethodBodyBuilder.transformNode(AstMethodBodyBuilder.java:392)
        //     at com.strobel.decompiler.languages.java.ast.AstMethodBodyBuilder.transformBlock(AstMethodBodyBuilder.java:333)
        //     at com.strobel.decompiler.languages.java.ast.AstMethodBodyBuilder.transformNode(AstMethodBodyBuilder.java:440)
        //     at com.strobel.decompiler.languages.java.ast.AstMethodBodyBuilder.transformBlock(AstMethodBodyBuilder.java:333)
        //     at com.strobel.decompiler.languages.java.ast.AstMethodBodyBuilder.transformNode(AstMethodBodyBuilder.java:425)
        //     at com.strobel.decompiler.languages.java.ast.AstMethodBodyBuilder.transformBlock(AstMethodBodyBuilder.java:333)
        //     at com.strobel.decompiler.languages.java.ast.AstMethodBodyBuilder.transformNode(AstMethodBodyBuilder.java:425)
        //     at com.strobel.decompiler.languages.java.ast.AstMethodBodyBuilder.transformBlock(AstMethodBodyBuilder.java:333)
        //     at com.strobel.decompiler.languages.java.ast.AstMethodBodyBuilder.createMethodBody(AstMethodBodyBuilder.java:294)
        //     at com.strobel.decompiler.languages.java.ast.AstMethodBodyBuilder.createMethodBody(AstMethodBodyBuilder.java:99)
        //     at com.strobel.decompiler.languages.java.ast.AstBuilder.createMethodBody(AstBuilder.java:782)
        //     at com.strobel.decompiler.languages.java.ast.AstBuilder.createMethod(AstBuilder.java:675)
        //     at com.strobel.decompiler.languages.java.ast.AstBuilder.addTypeMembers(AstBuilder.java:552)
        //     at com.strobel.decompiler.languages.java.ast.AstBuilder.createTypeCore(AstBuilder.java:519)
        //     at com.strobel.decompiler.languages.java.ast.AstBuilder.createTypeNoCache(AstBuilder.java:161)
        //     at com.strobel.decompiler.languages.java.ast.AstBuilder.createType(AstBuilder.java:150)
        //     at com.strobel.decompiler.languages.java.ast.AstBuilder.addType(AstBuilder.java:125)
        //     at com.strobel.decompiler.languages.java.JavaLanguage.buildAst(JavaLanguage.java:71)
        //     at com.strobel.decompiler.languages.java.JavaLanguage.decompileType(JavaLanguage.java:59)
        //     at com.strobel.decompiler.DecompilerDriver.decompileType(DecompilerDriver.java:330)
        //     at com.strobel.decompiler.DecompilerDriver.decompileJar(DecompilerDriver.java:251)
        //     at com.strobel.decompiler.DecompilerDriver.main(DecompilerDriver.java:126)
        // 
        throw new IllegalStateException("An error occurred while decompiling this method.");
    }
}
